OFHandlers/__init__.py
simpler_pickle-0.0.2.dist-info/LICENSE
simpler_pickle-0.0.2.dist-info/METADATA
simpler_pickle-0.0.2.dist-info/WHEEL
simpler_pickle-0.0.2.dist-info/top_level.txt
simpler_pickle-0.0.2.dist-info/RECORD
