Metadata-Version: 2.1
Name: simpler-pickle
Version: 0.0.2
Summary: simpler pickle code
Home-page: https://github.com/gariciodaro/simpler-pickle.git
Author: Gari Ciodaro Guerra
Author-email: gari.ciodaro.guerra@gmail.com
License: UNKNOWN
Platform: UNKNOWN
Classifier: Programming Language :: Python :: 3
Classifier: License :: OSI Approved :: MIT License
Classifier: Operating System :: OS Independent
Requires-Python: >=3.6
